{"attributes": {"cdm_data_type": {"type": "string", "data": "Trajectory"}, "cdm_trajectory_variables": {"type": "string", "data": "trajectory_id"}, "comment": {"type": "string", "data": ""}, "contributor_name": {"type": "string", "data": "Quinn, Patricia/NOAA-PMEL/Phone: 206-526-6892 /Address: 7600 Sand Pt. Wy. NE,Seattle,WA 98115 /email: Patricia.K.Quinn@noaa.gov"}, "creator_name": {"type": "string", "data": "\"Johnson, James\""}, "creator_email": {"type": "string", "data": "james.e.johnson@noaa.gov"}, "creator_url": {"type": "string", "data": ""}, "history": {"type": "string", "data": ""}, "platform": {"type": "string", "data": "RHBrown"}, "product_version": {"type": "string", "data": "0"}, "project": {"type": "string", "data": "ATOMIC"}, "sourceUrl": {"type": "string", "data": ""}, "title": {"type": "string", "data": "PMEL Atmospheric Chemistry ATOMIC total_mass data"}, "featureType": {"type": "string", "data": "Trajectory"}, "target_sample_rh": {"type": "string", "data": "55-60%"}, "infoUrl": {"type": "string", "data": "https://saga.pmel.noaa.gov/data/index.html"}}, "dimensions": "", "variables": {"time": {"type": "string", "attributes": {"_CoordinateAxisType": {"type": "string", "data": "Time"}, "axis": {"type": "string", "data": "T"}, "ioos_category": {"type": "string", "data": "Time"}, "long_name": {"type": "string", "data": "Datetime UTC"}, "standard_name": {"type": "string", "data": "time"}, "source_name": {"type": "string", "data": "datetime_utc"}, "time_origin": {"type": "string", "data": "01/01/1970 00:00"}, "time_precision": {"type": "string", "data": "1970-01-01T00:00:00Z"}, "units": {"type": "string", "data": "yyyy-MM-ddTHH:MM:ssZ"}}, "data": ["2020-01-07T22:02:00Z", "2020-01-08T13:56:00Z", "2020-01-09T01:40:00Z", "2020-01-09T12:08:00Z", "2020-01-10T12:02:00Z", "2020-01-11T11:50:00Z", "2020-01-12T11:54:00Z", "2020-01-13T13:21:00Z", "2020-01-14T13:17:00Z", "2020-01-15T12:40:00Z", "2020-01-16T13:35:00Z", "2020-01-17T12:15:00Z", "2020-01-19T00:15:00Z", "2020-01-19T22:58:00Z", "2020-01-20T22:55:00Z", "2020-01-21T22:54:00Z", "2020-01-23T10:30:00Z", "2020-01-24T18:20:00Z", "2020-01-29T02:57:00Z", "2020-01-29T23:50:00Z", "2020-01-31T00:43:00Z", "2020-01-31T23:15:00Z", "2020-02-01T23:35:00Z", "2020-02-02T23:57:00Z", "2020-02-06T21:09:00Z", "2020-02-07T23:33:00Z", "2020-02-08T23:20:00Z"], "shape": ["time"]}, "trajectory_id": {"type": "string", "shape": ["time"], "attributes": {"cf_role": {"type": "string", "data": "trajectory_id"}, "ioos_category": {"type": "string", "data": "Identifier"}, "long_name": {"type": "string", "data": "Trajectory ID"}}, "data": ["ATOMIC_RHBrown", "ATOMIC_RHBrown", "ATOMIC_RHBrown", "ATOMIC_RHBrown", "ATOMIC_RHBrown", "ATOMIC_RHBrown", "ATOMIC_RHBrown", "ATOMIC_RHBrown", "ATOMIC_RHBrown", "ATOMIC_RHBrown", "ATOMIC_RHBrown", "ATOMIC_RHBrown", "ATOMIC_RHBrown", "ATOMIC_RHBrown", "ATOMIC_RHBrown", "ATOMIC_RHBrown", "ATOMIC_RHBrown", "ATOMIC_RHBrown", "ATOMIC_RHBrown", "ATOMIC_RHBrown", "ATOMIC_RHBrown", "ATOMIC_RHBrown", "ATOMIC_RHBrown", "ATOMIC_RHBrown", "ATOMIC_RHBrown", "ATOMIC_RHBrown", "ATOMIC_RHBrown"]}, "duration": {"type": "int", "shape": ["time"], "attributes": {"long_name": {"type": "string", "data": "Duration"}, "units": {"type": "string", "data": "second"}}, "data": [43200.0, 36780.0, 31740.0, 80220.0, 80700.0, 81480.0, 81240.0, 76260.0, 76500.0, 77760.0, 75900.0, 79740.0, 78360.0, 82020.0, 82680.0, 75960.0, 41340.0, 92400.0, 68580.0, 77820.0, 76620.0, 82200.0, 81000.0, 68880.0, 89400.0, 80940.0, 131760.0]}, "latitude": {"type": "double", "shape": ["time"], "attributes": {"long_name": {"type": "string", "data": "Latitude"}, "units": {"type": "string", "data": "degrees_north"}, "instrument": {"type": "string", "data": "GPS"}, "source": {"type": "string", "data": "surface observation"}, "valid_min": {"type": "double", "data": -90.0}, "valid_max": {"type": "double", "data": 90.0}, "uncertainty": {"type": "string", "data": ""}, "standard_name": {"type": "string", "data": "latitude"}, "history": {"type": "string", "data": ""}, "comment": {"type": "string", "data": ""}, "description": {"type": "string", "data": ""}, "_CoordinateAxisType": {"type": "string", "data": "Lat"}, "axis": {"type": "string", "data": "Y"}, "ioos_category": {"type": "string", "data": "Location"}}, "data": [13.3258, 13.7646, 14.1585, 14.7188, 15.1547, 15.4627, 14.7387, 15.7467, 15.4851, 14.8082, 14.8414, 14.8471, 14.3509, 14.3506, 14.3635, 14.6179, 14.3776, 13.1416, 13.4898, 13.9426, 13.901, 13.9002, 13.9006, 13.9004, 13.4674, 14.0508, 13.8527]}, "longitude": {"type": "double", "shape": ["time"], "attributes": {"long_name": {"type": "string", "data": "Longitude"}, "units": {"type": "string", "data": "degrees_east"}, "instrument": {"type": "string", "data": "GPS"}, "source": {"type": "string", "data": "surface observation"}, "valid_min": {"type": "double", "data": -180.0}, "valid_max": {"type": "double", "data": 180.0}, "uncertainty": {"type": "string", "data": ""}, "standard_name": {"type": "string", "data": "longitude"}, "history": {"type": "string", "data": ""}, "comment": {"type": "string", "data": ""}, "description": {"type": "string", "data": ""}, "_CoordinateAxisType": {"type": "string", "data": "Lon"}, "axis": {"type": "string", "data": "X"}, "ioos_category": {"type": "string", "data": "Location"}}, "data": [-57.8479, -55.7187, -53.8068, -51.2397, -51.2602, -51.5369, -50.9842, -51.3551, -51.4072, -50.9607, -51.0207, -51.014, -53.0029, -53.0047, -53.0253, -52.8674, -55.0029, -59.072, -57.1814, -54.4921, -54.4994, -54.5005, -54.4999, -54.5003, -56.7338, -54.2625, -54.8625]}, "altitude": {"type": "double", "shape": ["time"], "attributes": {"long_name": {"type": "string", "data": "height above mean sea level"}, "units": {"type": "string", "data": "m"}, "instrument": {"type": "string", "data": ""}, "source": {"type": "string", "data": ""}, "valid_min": {"type": "double", "data": 0}, "valid_max": {"type": "double", "data": null}, "uncertainty": {"type": "string", "data": ""}, "standard_name": {"type": "string", "data": "altitude"}, "history": {"type": "string", "data": ""}, "comment": {"type": "string", "data": ""}, "description": {"type": "string", "data": ""}}, "data": [18.0, 18.0, 18.0, 18.0, 18.0, 18.0, 18.0, 18.0, 18.0, 18.0, 18.0, 18.0, 18.0, 18.0, 18.0, 18.0, 18.0, 18.0, 18.0, 18.0, 18.0, 18.0, 18.0, 18.0, 18.0, 18.0, 18.0]}, "mid_time": {"type": "string", "attributes": {"_CoordinateAxisType": {"type": "string", "data": "Time"}, "axis": {"type": "string", "data": "T"}, "ioos_category": {"type": "string", "data": "Time"}, "long_name": {"type": "string", "data": "midpoint Datetime UTC"}, "standard_name": {"type": "string", "data": "time"}, "source_name": {"type": "string", "data": "datetime_utc"}, "time_origin": {"type": "string", "data": "01/01/1970 00:00"}, "time_precision": {"type": "string", "data": "1970-01-01T00:00:00Z"}, "units": {"type": "string", "data": "yyyy-MM-ddTHH:MM:ssZ"}}, "data": ["2020-01-08T04:02:00Z", "2020-01-08T19:02:30Z", "2020-01-09T06:04:30Z", "2020-01-09T23:16:30Z", "2020-01-10T23:14:30Z", "2020-01-11T23:09:00Z", "2020-01-12T23:11:00Z", "2020-01-13T23:56:30Z", "2020-01-14T23:54:30Z", "2020-01-15T23:28:00Z", "2020-01-17T00:07:30Z", "2020-01-17T23:19:30Z", "2020-01-19T11:08:00Z", "2020-01-20T10:21:30Z", "2020-01-21T10:24:00Z", "2020-01-22T09:27:00Z", "2020-01-23T16:14:30Z", "2020-01-25T07:10:00Z", "2020-01-29T12:28:30Z", "2020-01-30T10:38:30Z", "2020-01-31T11:21:30Z", "2020-02-01T10:40:00Z", "2020-02-02T10:50:00Z", "2020-02-03T09:31:00Z", "2020-02-07T09:34:00Z", "2020-02-08T10:47:30Z", "2020-02-09T17:38:00Z"], "shape": ["time"]}, "end_time": {"type": "string", "attributes": {"_CoordinateAxisType": {"type": "string", "data": "Time"}, "axis": {"type": "string", "data": "T"}, "ioos_category": {"type": "string", "data": "Time"}, "long_name": {"type": "string", "data": "endpoint Datetime UTC"}, "standard_name": {"type": "string", "data": "time"}, "source_name": {"type": "string", "data": "datetime_utc"}, "time_origin": {"type": "string", "data": "01/01/1970 00:00"}, "time_precision": {"type": "string", "data": "1970-01-01T00:00:00Z"}, "units": {"type": "string", "data": "yyyy-MM-ddTHH:MM:ssZ"}}, "data": ["2020-01-08T10:02:00Z", "2020-01-09T00:09:00Z", "2020-01-09T10:29:00Z", "2020-01-10T10:25:00Z", "2020-01-11T10:27:00Z", "2020-01-12T10:28:00Z", "2020-01-13T10:28:00Z", "2020-01-14T10:32:00Z", "2020-01-15T10:32:00Z", "2020-01-16T10:16:00Z", "2020-01-17T10:40:00Z", "2020-01-18T10:24:00Z", "2020-01-19T22:01:00Z", "2020-01-20T21:45:00Z", "2020-01-21T21:53:00Z", "2020-01-22T20:00:00Z", "2020-01-23T21:59:00Z", "2020-01-25T20:00:00Z", "2020-01-29T22:00:00Z", "2020-01-30T21:27:00Z", "2020-01-31T22:00:00Z", "2020-02-01T22:05:00Z", "2020-02-02T22:05:00Z", "2020-02-03T19:05:00Z", "2020-02-07T21:59:00Z", "2020-02-08T22:02:00Z", "2020-02-10T11:56:00Z"], "shape": ["time"]}, "total_aerosol_mass_sub1": {"type": "double", "shape": ["time"], "attributes": {"long_name": {"type": "string", "data": "Particulate Fe Concentration for 1.1 um < Dp < 10 um, ug m-3"}, "units": {"type": "string", "data": "micrograms m-3"}, "instrument": {"type": "string", "data": "2-stage impactor"}, "source": {"type": "string", "data": "surface observation"}, "valid_min": {"type": "double", "data": ""}, "valid_max": {"type": "double", "data": ""}, "uncertainty": {"type": "string", "data": ""}, "standard_name": {"type": "string", "data": ""}, "history": {"type": "string", "data": ""}, "comment": {"type": "string", "data": ""}, "description": {"type": "string", "data": ""}}, "data": [4.72, 17.33, 2.38, 1.34, 0.7, 0.99, 1.51, 1.54, 1.22, 1.07, 0.77, 1.02, 1.27, 0.67, 0.68, 0.86, 1.14, 0.83, 4.97, 17.69, 11.84, 11.81, 13.87, 12.76, 3.15, 1.88, 7.68]}, "total_aerosol_mass_super1": {"type": "double", "shape": ["time"], "attributes": {"long_name": {"type": "string", "data": "Particulate Fe Concentration for 1.1 um < Dp < 10 um, ug m-3"}, "units": {"type": "string", "data": "micrograms m-3"}, "instrument": {"type": "string", "data": "2-stage impactor"}, "source": {"type": "string", "data": "surface observation"}, "valid_min": {"type": "double", "data": ""}, "valid_max": {"type": "double", "data": ""}, "uncertainty": {"type": "string", "data": ""}, "standard_name": {"type": "string", "data": ""}, "history": {"type": "string", "data": ""}, "comment": {"type": "string", "data": ""}, "description": {"type": "string", "data": ""}}, "data": [22.97, 68.1, 30.41, 21.44, 14.81, 21.35, 23.23, 48.0, 37.29, 36.8, 17.39, 25.97, 18.15, 14.01, 19.15, 28.94, 23.69, 6.67, 31.06, 65.26, 72.3, 61.11, 59.63, 45.5, 40.89, 24.36, 55.26]}}}